{
  "17896441": [
    "/17896441.5eb77786.css",
    "/17896441.f5520799.js"
  ],
  "main": [
    "/main.0e9d06af.css",
    "/main.a81c20af.js"
  ],
  "1be78505": [],
  "35000c2d": [
    "/35000c2d.45dd88e2.js"
  ],
  "3ef2b3a7": [
    "/3ef2b3a7.6cd87796.js"
  ],
  "4b017c35": [
    "/4b017c35.74b74dcf.js"
  ],
  "5fbc5cf1": [
    "/5fbc5cf1.26df6748.js"
  ],
  "72e14192": [
    "/72e14192.0a26cecb.js"
  ],
  "72ff2701": [
    "/72ff2701.61565e4c.js"
  ],
  "76944ddc": [
    "/76944ddc.1cf37a19.js"
  ],
  "7ccc7e0c": [
    "/7ccc7e0c.aa51ceeb.js"
  ],
  "8e33e675": [
    "/8e33e675.534ad8b9.js"
  ],
  "9c9e4252": [
    "/9c9e4252.6c7da31d.js"
  ],
  "a09c2993": [
    "/a09c2993.2d81ffe3.js"
  ],
  "b1627560": [
    "/b1627560.e6365965.js"
  ],
  "b94ec4b0": [
    "/b94ec4b0.cf130569.js"
  ],
  "c4f5d8e4": [
    "/c4f5d8e4.09217242.js"
  ],
  "cafbfab7": [
    "/cafbfab7.b12db146.js"
  ],
  "d0e36f78": [
    "/d0e36f78.c81fbb2b.js"
  ],
  "e2618210": [
    "/e2618210.20caf45a.js"
  ],
  "e6ccb422": [
    "/e6ccb422.2c0b8c64.js"
  ],
  "ef2910f4": [
    "/ef2910f4.42a065d7.js"
  ],
  "fdd1c05f": [
    "/fdd1c05f.2ae5e7c4.js"
  ]
}